sigma/__init__.py
sigma/azure_data_pipeline/client.py
sigma/congress/client.py
sigma/congress/fields.py
sigma/federal_register/client.py
sigma/federal_register/fields.py
sigma/finnews/client.py
sigma/finnews/cnbc.py
sigma/finnews/cnn_finance.py
sigma/finnews/fields.py
sigma/finnews/market_watch.py
sigma/finnews/nasdaq.py
sigma/finnews/news_enum.py
sigma/finnews/parser.py
sigma/finnews/seeking_alpha.py
sigma/finnews/sp_global.py
sigma/finnews/wsj.py
sigma/finnews/yahoo_finance.py
sigma/ibw/__init__.py
sigma/ibw/client.py
sigma/ibw/clientportal.py
sigma/pybea/__init__.py
sigma/pybea/client.py
sigma/pyrobot/indicators.py
sigma/pyrobot/portfolio.py
sigma/pyrobot/robot.py
sigma/pyrobot/stock_frame.py
sigma/pyrobot/trades.py
sigma/pysec/__init__.py
sigma/pysec/edgar.py
sigma/pysec/filing_types.py
sigma/pysec/parser.py
sigma/pysec/xbrl.py
sigma/pysec/parsing/__init__.py
sigma/td/__init__.py
sigma/td/client.py
sigma/td/enums.py
sigma/td/exceptions.py
sigma/td/message.py
sigma/td/oauth.py
sigma/td/option_chain.py
sigma/td/orders.py
sigma/td/stream.py
sigma/td/utils.py
sigma/td/watchlist_item.py
sigma/td/app/auth.py
sigma/ts/client.py
sigma.coding-0.1.0.dist-info/LICENSE
sigma.coding-0.1.0.dist-info/METADATA
sigma.coding-0.1.0.dist-info/WHEEL
sigma.coding-0.1.0.dist-info/top_level.txt
sigma.coding-0.1.0.dist-info/RECORD
