Metadata-Version: 2.1
Name: sigma.coding
Version: 0.1.0
Summary: A python client library used to leverage the different libraries provided by Sigma Coding.
Home-page: https://github.com/areed1192/sigma-coding
Author: Alex Reed
Author-email: coding.sigma@gmail.com
License: UNKNOWN
Keywords: sigma coding,governments,finance,APIs
Platform: UNKNOWN
Classifier: Development Status :: 3 - Alpha
Classifier: Intended Audience :: Developers
Classifier: Intended Audience :: Science/Research
Classifier: Intended Audience :: Financial and Insurance Industry
Classifier: License :: OSI Approved :: MIT License
Classifier: Natural Language :: English
Classifier: Operating System :: OS Independent
Classifier: Programming Language :: Python
Classifier: Programming Language :: Python :: 3
Classifier: Programming Language :: Python :: 3.8
Classifier: Topic :: Database
Classifier: Topic :: Education
Classifier: Topic :: Office/Business
Requires-Python: >=3.7
Requires-Dist: numpy (==1.19.0)
Requires-Dist: fake-useragent (==0.1.11)
Requires-Dist: certifi (==2020.6.20)
Requires-Dist: requests (==2.24.0)
Requires-Dist: pandas (==1.0.5)
Requires-Dist: urllib3 (==1.25.9)
Requires-Dist: websockets (==8.1)
Requires-Dist: requests-oauthlib (==1.3.0)
Requires-Dist: Flask (==1.0.2)
Requires-Dist: beautifulsoup4 (==4.9.1)
Requires-Dist: python-dateutil (==2.8.1)
